<BattleAction info="A ranged attack, line-of-sight, piercing">
  <baseAOERadius>0</baseAOERadius>
  <baseDelay>2.8</baseDelay>
  <baseFollowthroughStanceChangeDelay>2.8</baseFollowthroughStanceChangeDelay>
  <baseMinimumTargetingDistance>0</baseMinimumTargetingDistance>
  <baseTargetingRange>30</baseTargetingRange>
  <baseSPCost>29</baseSPCost>
  <alternateTargetSideFlags>0</alternateTargetSideFlags>
  <targetSideFlags>MyEnemies</targetSideFlags>
  <alternateTargetType>None</alternateTargetType>
  <targetType>LineOfSightPiercing</targetType>
  <categoryFlags>Attack</categoryFlags>
  <subactionOrder>atk0</subactionOrder>
  <animSkip>
    <animEvent info="">
      <animEventType>TestAnim_OnUse</animEventType>
      <fallbackType>None</fallbackType>
      <targetType>PrimaryTargets</targetType>
      <flags>WaitForMe</flags>
      <priority>0</priority>
    </animEvent>
    <animEvent info="">
      <animEventType>Hit</animEventType>
      <fallbackType>None</fallbackType>
      <targetType>SecondaryTargets</targetType>
      <flags>WaitForMe</flags>
      <priority>0</priority>
    </animEvent>
    <battleCameraScript>None</battleCameraScript>
  </animSkip>
  <Subaction info="">
    <eventBlock>
      <animEvent info="">
        <animEventType>TestAnim_OnUse</animEventType>
        <fallbackType>None</fallbackType>
        <targetType>PrimaryTargets</targetType>
        <flags>WaitForMe</flags>
        <priority>0</priority>
      </animEvent>
      <animEvent info="">
        <animEventType>Hit</animEventType>
        <fallbackType>None</fallbackType>
        <targetType>SecondaryTargets</targetType>
        <flags>WaitForMe</flags>
        <priority>0</priority>
      </animEvent>
      <battleCameraScript>None</battleCameraScript>
    </eventBlock>
    <subactionName>atk0</subactionName>
    <baseDamage>22</baseDamage>
    <baseAccuracy>0.9</baseAccuracy>
    <useAlternateTargetSet>False</useAlternateTargetSet>
    <atkStat>Stats_ATKHIT</atkStat>
    <defStat>Stat_DEF</defStat>
    <hitStat>Stat_HIT</hitStat>
    <evadeStat>Stat_EVA</evadeStat>
    <damageTypes>Thrust</damageTypes>
    <categoryFlags>Attack</categoryFlags>
    <damageDeterminantName>
    </damageDeterminantName>
    <successDeterminantName>
    </successDeterminantName>
  </Subaction>
</BattleAction>